juno/__init__.py
juno/additional_data.py
juno/attribute_getter.py
juno/balance.py
juno/card.py
juno/charge.py
juno/charge_object.py
juno/digital_account.py
juno/error_result.py
juno/exceptions.py
juno/notification.py
juno/onboarding.py
juno/payment.py
juno/payment_object.py
juno/plan.py
juno/plan_object.py
juno/sdk.py
juno/subscription.py
juno/subscription_object.py
juno/successful_result.py
juno/transfer.py
juno/utils.py
juno/resources/__init__.py
juno/resources/handler_request.py
juno/resources/requests_retry.py
juno/resources/routes/__init__.py
juno/resources/routes/additional_data_routes.py
juno/resources/routes/balance_routes.py
juno/resources/routes/card_routes.py
juno/resources/routes/charge_routes.py
juno/resources/routes/digital_account_routes.py
juno/resources/routes/notification_routes.py
juno/resources/routes/onboarding_routes.py
juno/resources/routes/payment_routes.py
juno/resources/routes/plan_routes.py
juno/resources/routes/subscription_routes.py
juno/resources/routes/transfer_routes.py
tests/__init__.py
tests/payment_test.py
tests/resources/__init__.py
tests/resources/juno_test.py
juno_python-0.4.1.dist-info/LICENSE
juno_python-0.4.1.dist-info/METADATA
juno_python-0.4.1.dist-info/WHEEL
juno_python-0.4.1.dist-info/top_level.txt
juno_python-0.4.1.dist-info/RECORD
