Metadata-Version: 2.1
Name: juno-python
Version: 0.4.1
Summary: Juno Python
Home-page: https://github.com/mjr/juno-python
Author: Manaia Junior
Author-email: manaiajr.23@gmail.com
License: MIT
Keywords: Payment,Juno
Platform: UNKNOWN
Classifier: Programming Language :: Python
Classifier: Programming Language :: Python :: 3
Classifier: Programming Language :: Python :: 3.7
License-File: LICENSE
Requires-Dist: requests (>=2.24.0)
